detvislib/__init__.py
detvislib/detvislib.py
DetVisLib-1.0.4.dist-info/LICENSE.md
DetVisLib-1.0.4.dist-info/LICENSE.py
DetVisLib-1.0.4.dist-info/METADATA
DetVisLib-1.0.4.dist-info/WHEEL
DetVisLib-1.0.4.dist-info/entry_points.txt
DetVisLib-1.0.4.dist-info/top_level.txt
DetVisLib-1.0.4.dist-info/RECORD
