Metadata-Version: 2.1
Name: DetVisLib
Version: 1.0.4
Summary: Detections Visualization Library - easy to use library to visualize detections from various object detection frameworks.
Home-page: https://github.com/Andropogon/DetVisLib
Author: Jan Gąsienica-Józkowy
Author-email: jgjozkowy@gmail.com
License: MIT
Platform: UNKNOWN
Classifier: License :: OSI Approved :: MIT License
Classifier: Programming Language :: Python :: 3.6
Classifier: Programming Language :: Python :: 3.7
Classifier: Programming Language :: Python :: 3.8
